ujimaru_markov_model/__init__.py
ujimaru_markov_model/cli.py
ujimaru_markov_model/data/ujimaru.json
ujimaru_markov_model/ujimaru.py
ujimaru_markov_model-0.3.0.dist-info/entry_points.txt
ujimaru_markov_model-0.3.0.dist-info/WHEEL
ujimaru_markov_model-0.3.0.dist-info/METADATA
ujimaru_markov_model-0.3.0.dist-info/RECORD
