Metadata-Version: 2.1
Name: ujimaru-markov-model
Version: 0.3.0
Summary: 
Author: hppRC
Author-email: hpp.ricecake@gmail.com
Requires-Python: >=3.8,<4.0
Classifier: Programming Language :: Python :: 3
Classifier: Programming Language :: Python :: 3.8
Requires-Dist: markovify (>=0.8.0,<0.9.0)
